pairformance/__init__.py
pairformance/bt.py
pairformance/core.py
pairformance/plotting_utils.py
pairformance/utils.py
pairformance-0.0.1.dist-info/LICENSE
pairformance-0.0.1.dist-info/METADATA
pairformance-0.0.1.dist-info/WHEEL
pairformance-0.0.1.dist-info/top_level.txt
pairformance-0.0.1.dist-info/RECORD
