Metadata-Version: 2.1
Name: pairformance
Version: 0.0.1
Summary: Tool to perform paired evaluation of automatic systems.
Home-page: https://github.com/epfl-dlab/pairformance
Author: Maxime Peyrard
Author-email: maxime.peyrard@epfl.ch
License: UNKNOWN
Platform: UNKNOWN
Classifier: Programming Language :: Python :: 3
Classifier: Programming Language :: Python :: 3.7
Classifier: Programming Language :: Python :: 3.8
Classifier: License :: OSI Approved :: Apache Software License
Classifier: Operating System :: OS Independent
Requires-Dist: matplotlib
Requires-Dist: numpy (>=1.10.4)
Requires-Dist: pandas
Requires-Dist: scipy (>=1.0.1)
Requires-Dist: seaborn (>=0.9.1)
